{
    "schema": "vitis_libraries_api_list_schema-1.0",
    "api_list": [
        {
            "api_name": "hls_foc_periodic_ap_fixed",
            "spec": {
                "schema": "vitis_libraries_api_list_schema-1.0",
                "api_name": "hls_foc_periodic_ap_fixed",
                "display_name": "SensorBasedFOC",
                "brief": "Level 1 : IP for Sensor Based FOC.",
                "target_domain": "PL",
                "visible": false,
                "header_file_name": [
                    "foc.hpp"
                ],
                "search_paths": [
                    "L1/include/hw"
                ],
                "instance": "function",
                "parameters": [],
                "ports": [
                    {
                        "name": "Ia",
                        "direction": "",
                        "type": "hls::stream<t_glb_foc2pwm>"
                    },
                    {
                        "name": "Ib",
                        "direction": "",
                        "type": "hls::stream<t_glb_foc2pwm>"
                    },
                    {
                        "name": "Ic",
                        "direction": "",
                        "type": "hls::stream<t_glb_foc2pwm>"
                    },
                    {
                        "name": "SPEED_THETA_m",
                        "direction": "",
                        "type": "hls::stream<t_glb_speed_theta>"
                    },
                    {
                        "name": "Va_cmd",
                        "direction": "",
                        "type": "hls::stream<t_glb_foc2pwm>"
                    },
                    {
                        "name": "Vb_cmd",
                        "direction": "",
                        "type": "hls::stream<t_glb_foc2pwm>"
                    },
                    {
                        "name": "Vc_cmd",
                        "direction": "",
                        "type": "hls::stream<t_glb_foc2pwm>"
                    },
                    {
                        "name": "control_mode_args",
                        "direction": "",
                        "type": "volatile int&"
                    },
                    {
                        "name": "control_fixperiod_args",
                        "direction": "",
                        "type": "volatile int&"
                    },
                    {
                        "name": "flux_sp_args",
                        "direction": "",
                        "type": "volatile int&"
                    },
                    {
                        "name": "flux_kp_args",
                        "direction": "",
                        "type": "volatile int&"
                    },
                    {
                        "name": "flux_ki_args",
                        "direction": "",
                        "type": "volatile int&"
                    },
                    {
                        "name": "flux_kd_args",
                        "direction": "",
                        "type": "volatile int&"
                    },
                    {
                        "name": "torque_sp_args",
                        "direction": "",
                        "type": "volatile int&"
                    },
                    {
                        "name": "torque_kp_args",
                        "direction": "",
                        "type": "volatile int&"
                    },
                    {
                        "name": "torque_ki_args",
                        "direction": "",
                        "type": "volatile int&"
                    },
                    {
                        "name": "torque_kd_args",
                        "direction": "",
                        "type": "volatile int&"
                    },
                    {
                        "name": "speed_sp_args",
                        "direction": "",
                        "type": "volatile int&"
                    },
                    {
                        "name": "speed_kp_args",
                        "direction": "",
                        "type": "volatile int&"
                    },
                    {
                        "name": "speed_ki_args",
                        "direction": "",
                        "type": "volatile int&"
                    },
                    {
                        "name": "speed_kd_args",
                        "direction": "",
                        "type": "volatile int&"
                    },
                    {
                        "name": "angle_sh_args",
                        "direction": "",
                        "type": "volatile int&"
                    },
                    {
                        "name": "vd_args",
                        "direction": "",
                        "type": "volatile int&"
                    },
                    {
                        "name": "vq_args",
                        "direction": "",
                        "type": "volatile int&"
                    },
                    {
                        "name": "fw_kp_args",
                        "direction": "",
                        "type": "volatile int&"
                    },
                    {
                        "name": "fw_ki_args",
                        "direction": "",
                        "type": "volatile int&"
                    },
                    {
                        "name": "id_stts",
                        "direction": "",
                        "type": "volatile int&"
                    },
                    {
                        "name": "flux_acc_stts",
                        "direction": "",
                        "type": "volatile int&"
                    },
                    {
                        "name": "flux_err_stts",
                        "direction": "",
                        "type": "volatile int&"
                    },
                    {
                        "name": "flux_out_stts",
                        "direction": "",
                        "type": "volatile int&"
                    },
                    {
                        "name": "iq_stts",
                        "direction": "",
                        "type": "volatile int&"
                    },
                    {
                        "name": "torque_acc_stts",
                        "direction": "",
                        "type": "volatile int&"
                    },
                    {
                        "name": "torque_err_stts",
                        "direction": "",
                        "type": "volatile int&"
                    },
                    {
                        "name": "torque_out_stts",
                        "direction": "",
                        "type": "volatile int&"
                    },
                    {
                        "name": "speed_stts",
                        "direction": "",
                        "type": "volatile int&"
                    },
                    {
                        "name": "speed_acc_stts",
                        "direction": "",
                        "type": "volatile int&"
                    },
                    {
                        "name": "speed_err_stts",
                        "direction": "",
                        "type": "volatile int&"
                    },
                    {
                        "name": "speed_out_stts",
                        "direction": "",
                        "type": "volatile int&"
                    },
                    {
                        "name": "angle_stts",
                        "direction": "",
                        "type": "volatile int&"
                    },
                    {
                        "name": "Va_cmd_stts",
                        "direction": "",
                        "type": "volatile int&"
                    },
                    {
                        "name": "Vb_cmd_stts",
                        "direction": "",
                        "type": "volatile int&"
                    },
                    {
                        "name": "Vc_cmd_stts",
                        "direction": "",
                        "type": "volatile int&"
                    },
                    {
                        "name": "Ialpha_stts",
                        "direction": "",
                        "type": "volatile int&"
                    },
                    {
                        "name": "Ibeta_stts",
                        "direction": "",
                        "type": "volatile int&"
                    },
                    {
                        "name": "Ihomopolar_stts",
                        "direction": "",
                        "type": "volatile int&"
                    },
                    {
                        "name": "trip_cnt",
                        "direction": "",
                        "type": "volatile int&"
                    }
                ]
            },
            "target_domain": "PL"
        },
        {
            "api_name": "hls_qei",
            "spec": {
                "schema": "vitis_libraries_api_list_schema-1.0",
                "api_name": "hls_qei",
                "display_name": "hls_qei_axi",
                "brief": "Level 1: IP for Quadrature Encoder Interface",
                "target_domain": "PL",
                "visible": false,
                "header_file_name": [
                    "qei.hpp"
                ],
                "search_paths": [
                    "L1/include/hw"
                ],
                "instance": "function",
                "parameters": [],
                "ports": [
                    {
                        "name": "qei_A",
                        "direction": "",
                        "type": "hls::stream<t_bin_qei>"
                    },
                    {
                        "name": "qei_B",
                        "direction": "",
                        "type": "hls::stream<t_bin_qei>"
                    },
                    {
                        "name": "qei_I",
                        "direction": "",
                        "type": "hls::stream<t_bin_qei>"
                    },
                    {
                        "name": "qei_RPM_THETA_m",
                        "direction": "",
                        "type": "hls::stream<ap_uint<32> >"
                    },
                    {
                        "name": "qei_dir",
                        "direction": "",
                        "type": "hls::stream<t_bin_qei>"
                    },
                    {
                        "name": "qei_err",
                        "direction": "",
                        "type": "hls::stream<t_err_qei>"
                    },
                    {
                        "name": "qei_args_cpr",
                        "direction": "",
                        "type": "volatile int&"
                    },
                    {
                        "name": "qei_args_ctrl",
                        "direction": "",
                        "type": "volatile int&"
                    },
                    {
                        "name": "qei_stts_RPM_THETA_m",
                        "direction": "",
                        "type": "volatile int&"
                    },
                    {
                        "name": "qei_stts_dir",
                        "direction": "",
                        "type": "volatile int&"
                    },
                    {
                        "name": "qei_stts_err",
                        "direction": "",
                        "type": "volatile int&"
                    }
                ]
            },
            "target_domain": "PL"
        },
        {
            "api_name": "hls_pwm_gen",
            "spec": {
                "schema": "vitis_libraries_api_list_schema-1.0",
                "api_name": "hls_pwm_gen_axi",
                "display_name": "hls_pwm_gen",
                "brief": "Pulse wave modulation generator",
                "target_domain": "PL",
                "visible": false,
                "header_file_name": [
                    "svpwm.hpp"
                ],
                "search_paths": [
                    "L1/tests/IP_SVPWM/src",
                    "L1/include/hw"
                ],
                "instance": "function",
                "parameters": [],
                "ports": [
                    {
                        "name": "strm_duty_ratio_a",
                        "direction": "In",
                        "type": "hls::stream<t_svpwm_ratio >"
                    },
                    {
                        "name": "strm_duty_ratio_b",
                        "direction": "In",
                        "type": "hls::stream<t_svpwm_ratio >"
                    },
                    {
                        "name": "strm_duty_ratio_c",
                        "direction": "In",
                        "type": "hls::stream<t_svpwm_ratio >"
                    },
                    {
                        "name": "strm_pwm_h_a",
                        "direction": "Out",
                        "type": "hls::stream<ap_uint<1> >"
                    },
                    {
                        "name": "strm_pwm_h_b",
                        "direction": "Out",
                        "type": "hls::stream<ap_uint<1> >"
                    },
                    {
                        "name": "strm_pwm_h_c",
                        "direction": "Out",
                        "type": "hls::stream<ap_uint<1> >"
                    },
                    {
                        "name": "strm_pwm_l_a",
                        "direction": "Out",
                        "type": "hls::stream<ap_uint<1> >"
                    },
                    {
                        "name": "strm_pwm_l_b",
                        "direction": "Out",
                        "type": "hls::stream<ap_uint<1> >"
                    },
                    {
                        "name": "strm_pwm_l_c",
                        "direction": "Out",
                        "type": "hls::stream<ap_uint<1> >"
                    },
                    {
                        "name": "strm_pwm_sync_a",
                        "direction": "Out",
                        "type": "hls::stream<ap_uint<1> >"
                    },
                    {
                        "name": "strm_pwm_sync_b",
                        "direction": "Out",
                        "type": "hls::stream<ap_uint<1> >"
                    },
                    {
                        "name": "strm_pwm_sync_c",
                        "direction": "Out",
                        "type": "hls::stream<ap_uint<1> >"
                    },
                    {
                        "name": "pwm_args_pwm_freq",
                        "direction": "In",
                        "type": "volatile int&"
                    },
                    {
                        "name": "pwm_args_dead_cycles",
                        "direction": "In",
                        "type": "volatile int&"
                    },
                    {
                        "name": "pwm_args_phase_shift",
                        "direction": "In",
                        "type": "volatile int&"
                    },
                    {
                        "name": "pwm_stt_pwm_cycle",
                        "direction": "In",
                        "type": "volatile int&"
                    },
                    {
                        "name": "pwm_args_sample_ii",
                        "direction": "In",
                        "type": "volatile int&"
                    }
                ]
            },
            "target_domain": "PL"
        }
    ]
}