{
    "schema": "vitis_libraries_api_list_schema-1.0",
    "api_list": [
        {
            "api_name": "xf::solver::geqrf",
            "spec": {
                "schema": "vitis_libraries_api_list_schema-1.0",
                "api_name": "xf::solver::geqrf",
                "display_name": "geqrf",
                "brief": "This function computes QR decomposition of matrix",
                "target_domain": "PL",
                "header_file_name": [
                    "geqrf.hpp"
                ],
                "search_paths": [
                    "L2/include",
                    "L2/include/hw/MatrixDecomposition"
                ],
                "instance": "function",
                "parameters": [
                    {
                        "name": "T",
                        "type": "typename",
                        "description": "data type (support float and double)"
                    },
                    {
                        "name": "NRMAX",
                        "type": "int",
                        "description": "maximum number of rows of input matrix"
                    },
                    {
                        "name": "NCMAX",
                        "type": "int",
                        "description": "maximum number of columns of input matrix"
                    },
                    {
                        "name": "NCU",
                        "type": "int",
                        "description": "number of computation unit"
                    }
                ],
                "ports": [
                    {
                        "name": "m",
                        "direction": "input",
                        "type": "int"
                    },
                    {
                        "name": "n",
                        "direction": "input",
                        "type": "int"
                    },
                    {
                        "name": "A",
                        "direction": "input",
                        "type": "T *"
                    },
                    {
                        "name": "lda",
                        "direction": "input",
                        "type": "int"
                    },
                    {
                        "name": "tau",
                        "direction": "output",
                        "type": "T *"
                    }
                ],
                "visible": false
            },
            "target_domain": "PL"
        },
        {
            "api_name": "xf::solver::gesvdj_2D",
            "spec": {
                "schema": "vitis_libraries_api_list_schema-1.0",
                "api_name": "xf::solver::gesvdj_2D",
                "display_name": "gesvdj_2D",
                "brief": "",
                "target_domain": "PL",
                "header_file_name": [
                    "gesvdj.hpp"
                ],
                "search_paths": [
                    "L2/include",
                    "L2/include/hw/MatrixDecomposition"
                ],
                "instance": "function",
                "parameters": [
                    {
                        "name": "T",
                        "type": "typename",
                        "description": "data type"
                    },
                    {
                        "name": "diagSize",
                        "type": "int",
                        "description": "size of matrix diagonal matrix"
                    },
                    {
                        "name": "UN",
                        "type": "int",
                        "description": "Unroll number"
                    },
                    {
                        "name": "NMAXUN",
                        "type": "int",
                        "description": "size for each unrolled CU"
                    }
                ],
                "ports": [],
                "visible": false
            },
            "target_domain": "PL"
        },
        {
            "api_name": "xf::solver::gesvdj",
            "spec": {
                "schema": "vitis_libraries_api_list_schema-1.0",
                "api_name": "xf::solver::gesvdj",
                "display_name": "gesvdj",
                "brief": "Symmetric Matrix Jacobi based Singular Value Decomposition (GESVDJ) .",
                "target_domain": "PL",
                "header_file_name": [
                    "gesvdj.hpp"
                ],
                "search_paths": [
                    "L2/include",
                    "L2/include/hw/MatrixDecomposition"
                ],
                "instance": "function",
                "parameters": [
                    {
                        "name": "T",
                        "type": "typename",
                        "description": "data type (support float and double)."
                    },
                    {
                        "name": "NMAX",
                        "type": "int",
                        "description": "maximum number of rows/columns of input matrix"
                    },
                    {
                        "name": "NCU",
                        "type": "int",
                        "description": "number of computation unit"
                    }
                ],
                "ports": [
                    {
                        "name": "m",
                        "direction": "input",
                        "type": "int"
                    },
                    {
                        "name": "A",
                        "direction": "input",
                        "type": "T *"
                    },
                    {
                        "name": "S",
                        "direction": "output",
                        "type": "T *"
                    },
                    {
                        "name": "U",
                        "direction": "output",
                        "type": "T *"
                    },
                    {
                        "name": "V",
                        "direction": "output",
                        "type": "T *"
                    },
                    {
                        "name": "lda",
                        "direction": "input",
                        "type": "int"
                    },
                    {
                        "name": "ldu",
                        "direction": "input",
                        "type": "int"
                    },
                    {
                        "name": "ldv",
                        "direction": "input",
                        "type": "int"
                    },
                    {
                        "name": "info",
                        "direction": "output",
                        "type": "int &"
                    }
                ],
                "visible": false
            },
            "target_domain": "PL"
        },
        {
            "api_name": "xf::solver::gesvj",
            "spec": {
                "schema": "vitis_libraries_api_list_schema-1.0",
                "api_name": "xf::solver::gesvj",
                "display_name": "gesvj",
                "brief": "This function implements singular value decomposition of matrix A using one-sided Jacobi algorihtm.",
                "target_domain": "PL",
                "header_file_name": [
                    "gesvj.hpp"
                ],
                "search_paths": [
                    "L2/include",
                    "L2/include/hw/MatrixDecomposition"
                ],
                "instance": "function",
                "parameters": [
                    {
                        "name": "T",
                        "type": "typename",
                        "description": "the data type of gesvj"
                    },
                    {
                        "name": "NRMAX",
                        "type": "int",
                        "description": "maximum number of rows of input matrix"
                    },
                    {
                        "name": "NCMAX",
                        "type": "int",
                        "description": "maximum number of columns of input matrix"
                    },
                    {
                        "name": "MCU",
                        "type": "int",
                        "description": "number of computation unit of M"
                    },
                    {
                        "name": "NCU",
                        "type": "int",
                        "description": "number of computation unit of N"
                    }
                ],
                "ports": [
                    {
                        "name": "m",
                        "direction": "input",
                        "type": "int"
                    },
                    {
                        "name": "n",
                        "direction": "input",
                        "type": "int"
                    },
                    {
                        "name": "A",
                        "direction": "input",
                        "type": "T *"
                    },
                    {
                        "name": "S",
                        "direction": "output",
                        "type": "T *"
                    },
                    {
                        "name": "U",
                        "direction": "output",
                        "type": "T *"
                    },
                    {
                        "name": "V",
                        "direction": "output",
                        "type": "T *"
                    }
                ],
                "visible": false
            },
            "target_domain": "PL"
        },
        {
            "api_name": "xf::solver::getrf",
            "spec": {
                "schema": "vitis_libraries_api_list_schema-1.0",
                "api_name": "xf::solver::getrf",
                "display_name": "getrf",
                "brief": "This function computes the LU decomposition (with partial pivoting) of matrix",
                "target_domain": "PL",
                "header_file_name": [
                    "getrf.hpp"
                ],
                "search_paths": [
                    "L2/include",
                    "L2/include/hw/MatrixDecomposition"
                ],
                "instance": "function",
                "parameters": [
                    {
                        "name": "T",
                        "type": "typename",
                        "description": "data type (support float and double)"
                    },
                    {
                        "name": "NMAX",
                        "type": "int",
                        "description": "maximum number of rows/columns of input matrix"
                    },
                    {
                        "name": "NCU",
                        "type": "int",
                        "description": "number of computation unit"
                    }
                ],
                "ports": [
                    {
                        "name": "n",
                        "direction": "input",
                        "type": "int"
                    },
                    {
                        "name": "A",
                        "direction": "inout",
                        "type": "T *"
                    },
                    {
                        "name": "lda",
                        "direction": "input",
                        "type": "int"
                    },
                    {
                        "name": "pivot",
                        "direction": "output",
                        "type": "int"
                    },
                    {
                        "name": "info",
                        "direction": "output",
                        "type": "int &"
                    }
                ],
                "visible": true
            },
            "target_domain": "PL"
        },
        {
            "api_name": "xf::solver::getrf_nopivot",
            "spec": {
                "schema": "vitis_libraries_api_list_schema-1.0",
                "api_name": "xf::solver::getrf_nopivot",
                "display_name": "getrf_nopivot",
                "brief": "This function computes the LU decomposition (without pivoting) of matrix",
                "target_domain": "PL",
                "header_file_name": [
                    "getrf_nopivot.hpp"
                ],
                "search_paths": [
                    "L2/include",
                    "L2/include/hw/MatrixDecomposition"
                ],
                "instance": "function",
                "parameters": [
                    {
                        "name": "T",
                        "type": "typename",
                        "description": "data type (support float and double)"
                    },
                    {
                        "name": "NMAX",
                        "type": "int",
                        "description": "maximum number of rows/cols of input matrix"
                    },
                    {
                        "name": "NCU",
                        "type": "int",
                        "description": "number of computation unit"
                    }
                ],
                "ports": [
                    {
                        "name": "n",
                        "direction": "input",
                        "type": "int"
                    },
                    {
                        "name": "A",
                        "direction": "inout",
                        "type": "T*"
                    },
                    {
                        "name": "lda",
                        "direction": "input",
                        "type": "int"
                    },
                    {
                        "name": "info",
                        "direction": "output",
                        "type": "int&"
                    }
                ],
                "visible": true
            },
            "target_domain": "PL"
        },
        {
            "api_name": "xf::solver::potrf",
            "spec": {
                "schema": "vitis_libraries_api_list_schema-1.0",
                "api_name": "xf::solver::potrf",
                "display_name": "potrf",
                "brief": "This function computes the Cholesky decomposition of matrix",
                "target_domain": "PL",
                "header_file_name": [
                    "potrf.hpp"
                ],
                "search_paths": [
                    "L2/include",
                    "L2/include/hw/MatrixDecomposition"
                ],
                "instance": "function",
                "parameters": [
                    {
                        "name": "T",
                        "type": "typename",
                        "description": "data type (support float and double)"
                    },
                    {
                        "name": "NMAX",
                        "type": "int",
                        "description": "maximum number of rows/columns of input matrix"
                    },
                    {
                        "name": "NCU",
                        "type": "int",
                        "description": "number of computation unit"
                    }
                ],
                "ports": [
                    {
                        "name": "m",
                        "direction": "input",
                        "type": "int"
                    },
                    {
                        "name": "A",
                        "direction": "inout",
                        "type": "T *"
                    },
                    {
                        "name": "lda",
                        "direction": "input",
                        "type": "int"
                    },
                    {
                        "name": "info",
                        "direction": "output",
                        "type": "int &"
                    }
                ],
                "visible": true
            },
            "target_domain": "PL"
        },
        {
            "api_name": "xf::solver::gelinearsolver",
            "spec": {
                "schema": "vitis_libraries_api_list_schema-1.0",
                "api_name": "xf::solver::gelinearsolver",
                "display_name": "gelinearsolver",
                "brief": "This function solves a system of linear equation with general *matrix along with multiple right-hand side vector",
                "target_domain": "PL",
                "header_file_name": [
                    "gelinearsolver.hpp"
                ],
                "search_paths": [
                    "L2/include",
                    "L2/include/hw/LinearSolver"
                ],
                "instance": "function",
                "parameters": [
                    {
                        "name": "T",
                        "type": "typename",
                        "description": "data type (support float and double)"
                    },
                    {
                        "name": "NMAX",
                        "type": "int",
                        "description": "maximum number of rows/columns of input matrix"
                    },
                    {
                        "name": "NCU",
                        "type": "int",
                        "description": "number of computation unit"
                    }
                ],
                "ports": [
                    {
                        "name": "n",
                        "direction": "input",
                        "type": "int"
                    },
                    {
                        "name": "A",
                        "direction": "inout",
                        "type": "T*"
                    },
                    {
                        "name": "b",
                        "direction": "input",
                        "type": "int"
                    },
                    {
                        "name": "B",
                        "direction": "inout",
                        "type": "T*"
                    },
                    {
                        "name": "lda",
                        "direction": "input",
                        "type": "int"
                    },
                    {
                        "name": "ldb",
                        "direction": "input",
                        "type": "int"
                    },
                    {
                        "name": "info",
                        "direction": "output",
                        "type": "int&"
                    }
                ],
                "visible": true
            },
            "target_domain": "PL"
        },
        {
            "api_name": "xf::solver::gematrixinverse",
            "spec": {
                "schema": "vitis_libraries_api_list_schema-1.0",
                "api_name": "xf::solver::gematrixinverse",
                "display_name": "gematrixinverse",
                "brief": "This function computes the inverse matrix of",
                "target_domain": "PL",
                "header_file_name": [
                    "gematrixinverse.hpp"
                ],
                "search_paths": [
                    "L2/include",
                    "L2/include/hw/LinearSolver"
                ],
                "instance": "function",
                "parameters": [
                    {
                        "name": "T",
                        "type": "typename",
                        "description": "data type (support float and double)"
                    },
                    {
                        "name": "NMAX",
                        "type": "int",
                        "description": "maximum number of rows/columns of input matrix"
                    },
                    {
                        "name": "NCU",
                        "type": "int",
                        "description": "number of computation unit"
                    }
                ],
                "ports": [
                    {
                        "name": "m",
                        "direction": "input",
                        "type": "int"
                    },
                    {
                        "name": "A",
                        "direction": "inout",
                        "type": "T *"
                    },
                    {
                        "name": "lda",
                        "direction": "input",
                        "type": "int"
                    },
                    {
                        "name": "info",
                        "direction": "output",
                        "type": "int &"
                    }
                ],
                "visible": true
            },
            "target_domain": "PL"
        },
        {
            "api_name": "xf::solver::gtsv",
            "spec": {
                "schema": "vitis_libraries_api_list_schema-1.0",
                "api_name": "xf::solver::gtsv",
                "display_name": "gtsv",
                "brief": "Tri-diagonal linear solver. Compute solution to linear system with a tridiagonal matrix. Parallel Cyclic Reduction method.",
                "target_domain": "PL",
                "header_file_name": [
                    "gtsv_pcr.hpp"
                ],
                "search_paths": [
                    "L2/include",
                    "L2/include/hw/LinearSolver"
                ],
                "instance": "function",
                "parameters": [
                    {
                        "name": "T",
                        "type": "typename",
                        "description": "data type (support float and double)"
                    },
                    {
                        "name": "NMAX",
                        "type": "unsigned int",
                        "description": "matrix size"
                    },
                    {
                        "name": "NCU",
                        "type": "unsigned int",
                        "description": "number of compute units"
                    }
                ],
                "ports": [
                    {
                        "name": "n",
                        "direction": "input",
                        "type": "unsigned int,"
                    },
                    {
                        "name": "matDiagLow",
                        "direction": "inout",
                        "type": "T*"
                    },
                    {
                        "name": "matDiag",
                        "direction": "inout",
                        "type": "T*"
                    },
                    {
                        "name": "matDiagUp",
                        "direction": "inout",
                        "type": "T*"
                    },
                    {
                        "name": "rhs",
                        "direction": "inout",
                        "type": "T*"
                    }
                ],
                "visible": false
            },
            "target_domain": "PL"
        },
        {
            "api_name": "xf::solver::polinearsolver",
            "spec": {
                "schema": "vitis_libraries_api_list_schema-1.0",
                "api_name": "xf::solver::polinearsolver",
                "display_name": "polinearsolver",
                "brief": "This function solves a system of linear equation with symmetric positive definite (SPD) matrix along with multiple right-hand side vector",
                "target_domain": "PL",
                "header_file_name": [
                    "polinearsolver.hpp"
                ],
                "search_paths": [
                    "L2/include",
                    "L2/include/hw/LinearSolver"
                ],
                "instance": "function",
                "parameters": [
                    {
                        "name": "T",
                        "type": "typename",
                        "description": "data type (support float and double)"
                    },
                    {
                        "name": "NMAX",
                        "type": "int",
                        "description": "maximum number of rows/columns of input matrix"
                    },
                    {
                        "name": "NCU",
                        "type": "int",
                        "description": "number of computation unit"
                    }
                ],
                "ports": [
                    {
                        "name": "n",
                        "direction": "input",
                        "type": "int"
                    },
                    {
                        "name": "A",
                        "direction": "inout",
                        "type": "T*"
                    },
                    {
                        "name": "b",
                        "direction": "input",
                        "type": "int"
                    },
                    {
                        "name": "B",
                        "direction": "inout",
                        "type": "T*"
                    },
                    {
                        "name": "lda",
                        "direction": "input",
                        "type": "int"
                    },
                    {
                        "name": "ldb",
                        "direction": "input",
                        "type": "int"
                    },
                    {
                        "name": "info",
                        "direction": "output",
                        "type": "int*"
                    }
                ],
                "visible": true
            },
            "target_domain": "PL"
        },
        {
            "api_name": "xf::solver::pomatrixinverse",
            "spec": {
                "schema": "vitis_libraries_api_list_schema-1.0",
                "api_name": "xf::solver::pomatrixinverse",
                "display_name": "pomatrixinverse",
                "brief": "This function computes the inverse matrix of",
                "target_domain": "PL",
                "header_file_name": [
                    "pomatrixinverse.hpp"
                ],
                "search_paths": [
                    "L2/include",
                    "L2/include/hw/LinearSolver"
                ],
                "instance": "function",
                "parameters": [
                    {
                        "name": "T",
                        "type": "typename",
                        "description": "data type (support float and double)"
                    },
                    {
                        "name": "NMAX",
                        "type": "int",
                        "description": "maximum number of rows/columns of input matrix"
                    },
                    {
                        "name": "NCU",
                        "type": "int",
                        "description": "number of computation unit"
                    }
                ],
                "ports": [
                    {
                        "name": "m",
                        "direction": "",
                        "type": "int"
                    },
                    {
                        "name": "A",
                        "direction": "",
                        "type": "T *"
                    },
                    {
                        "name": "lda",
                        "direction": "",
                        "type": "int"
                    },
                    {
                        "name": "info",
                        "direction": "",
                        "type": "int &"
                    }
                ],
                "visible": true
            },
            "target_domain": "PL"
        },
        {
            "api_name": "xf::solver::trtrs",
            "spec": {
                "schema": "vitis_libraries_api_list_schema-1.0",
                "api_name": "xf::solver::trtrs",
                "display_name": "trtrs",
                "brief": "This function solves a system of linear equation with triangular coefficient matrix along with multiple right-hand side vector",
                "target_domain": "PL",
                "header_file_name": [
                    "trtrs.hpp"
                ],
                "search_paths": [
                    "L2/include",
                    "L2/include/hw/LinearSolver"
                ],
                "instance": "function",
                "parameters": [
                    {
                        "name": "T",
                        "type": "typename",
                        "description": "data type (support float and double)"
                    },
                    {
                        "name": "NMAX",
                        "type": "int",
                        "description": "maximum number of rows/columns of input matrix"
                    },
                    {
                        "name": "NCU",
                        "type": "int",
                        "description": "number of computation unit"
                    }
                ],
                "ports": [
                    {
                        "name": "m",
                        "direction": "input",
                        "type": "char"
                    },
                    {
                        "name": "A",
                        "direction": "inout",
                        "type": "T *"
                    },
                    {
                        "name": "b",
                        "direction": "int",
                        "type": "int"
                    },
                    {
                        "name": "B",
                        "direction": "inout",
                        "type": "int"
                    },
                    {
                        "name": "lda",
                        "direction": "input",
                        "type": "int"
                    },
                    {
                        "name": "ldb",
                        "direction": "input",
                        "type": "int"
                    },
                    {
                        "name": "info",
                        "direction": "output",
                        "type": "int &"
                    }
                ],
                "visible": false
            },
            "target_domain": "PL"
        },
        {
            "api_name": "xf::solver::syevj",
            "spec": {
                "schema": "vitis_libraries_api_list_schema-1.0",
                "api_name": "xf::solver::syevj",
                "display_name": "syevj",
                "brief": "Symmetric Matrix Jacobi based Eigenvalue Decomposition (SYEVJ) .",
                "target_domain": "PL",
                "header_file_name": [
                    "syevj.hpp"
                ],
                "search_paths": [
                    "L2/include",
                    "L2/include/hw/EigenSolver"
                ],
                "instance": "function",
                "parameters": [
                    {
                        "name": "T",
                        "type": "typename",
                        "description": "data type (support float and double)."
                    },
                    {
                        "name": "NMAX",
                        "type": "int",
                        "description": "maximum number of rows/columns of input matrix"
                    },
                    {
                        "name": "NCU",
                        "type": "int",
                        "description": "number of computation unit"
                    }
                ],
                "ports": [
                    {
                        "name": "m",
                        "direction": "input",
                        "type": "int"
                    },
                    {
                        "name": "A",
                        "direction": "input",
                        "type": "T *"
                    },
                    {
                        "name": "S",
                        "direction": "output",
                        "type": "T *"
                    },
                    {
                        "name": "U",
                        "direction": "output",
                        "type": "T *"
                    },
                    {
                        "name": "lda",
                        "direction": "input",
                        "type": "int"
                    },
                    {
                        "name": "ldu",
                        "direction": "input",
                        "type": "int"
                    },
                    {
                        "name": "info",
                        "direction": "output",
                        "type": "int &"
                    }
                ],
                "visible": false
            },
            "target_domain": "PL"
        },
        {
            "api_name": "xf::solver::aie::cholesky::cholesky_graph",
            "target_domain": "AIE",
            "spec": {
                "brief": "Cholesky decomposition with float/cfloat data type.",
                "search_paths": [
                    "L1/include/aie",
                    "L1/src/aie",
                    "L2/include/aie"
                ],
                "visible": true,
                "target_domain": "AIE",
                "display_name": "cholesky",
                "parameters": [
                    {
                        "type": "typename",
                        "name": "TT_DATA",
                        "description": "The type of individual data samples input to port."
                    },
                    {
                        "type": "unsigned int",
                        "name": "TP_DIM",
                        "description": "The dimension size of the matrix."
                    },
                    {
                        "type": "unsigned int",
                        "name": "TP_NUM_FRAMES",
                        "description": "The number of operations per call to the kernel"
                    },
                    {
                        "type": "unsigned int",
                        "name": "TP_GRID_DIM",
                        "description": "The dimension size of the grid of kernels used to break up a matrix."
                    }
                ],
                "header_file_name": [
                    "cholesky_graph.hpp"
                ],
                "instance": "class",
                "api_name": "xf::solver::aie::cholesky::cholesky_graph",
                "ports": [
                    {
                        "direction": "input",
                        "type": "input_port xf::solver::aie::cholesky::cholesky_graph< TT_DATA, TP_DIM, TP_NUM_FRAMES, TP_NUM_FRAMES, TP_GRID_DIM>::in",
                        "name": "in"
                    },
                    {
                        "direction": "output",
                        "type": "output_port xf::solver::aie::cholesky::cholesky_graph< TT_DATA, TP_DIM, TP_NUM_FRAMES, TP_NUM_FRAMES, TP_GRID_DIM>::out",
                        "name": "out"
                    }
                ],
                "schema": "vitis_libraries_api_list_schema-1.0"
            }
        },
        {
            "api_name": "xf::solver::aie::qrd::qrd_graph",
            "target_domain": "AIE",
            "spec": {
                "brief": "QR decomposition with float/cfloat data type.",
                "search_paths": [
                    "L1/include/aie",
                    "L1/src/aie",
                    "L2/include/aie"
                ],
                "visible": true,
                "target_domain": "AIE",
                "display_name": "qrd_graph",
                "parameters": [
                    {
                        "type": "typename",
                        "name": "TT_DATA",
                        "description": "The type of individual data samples input to port A."
                    },
                    {
                        "type": "unsigned int",
                        "name": "TP_DIM_ROWS",
                        "description": "Row dimension of the input matrix."
                    },
                    {
                        "type": "unsigned int",
                        "name": "TP_DIM_COLS",
                        "description": "Column dimension of the input matrix."
                    },
                    {
                        "type": "unsigned int",
                        "name": "TP_NUM_FRAMES",
                        "description": "The number of operations per call to the kernel."
                    },
                    {
                        "type": "unsigned int",
                        "name": "TP_CASC_LEN",
                        "description": "The number of cascaded kernels to be used to perform the function."
                    },     
                    {
                        "type": "unsigned int",
                        "name": "TP_DIM_A_LEADING",
                        "description": "Describes which dimension of the Matrix A input data is contigious in memory. TP_DIM_A_LEADING=1 is row major, and TP_DIM_A_LEADING=0 is column major."
                    },                    
                    {
                        "type": "unsigned int",
                        "name": "TP_DIM_Q_LEADING",
                        "description": "Describes which dimension of the Matrix Q output data is contigious in memory. TP_DIM_Q_LEADING=1 is row major, and TP_DIM_Q_LEADING=0 is column major."  
                    },
                    {
                        "type": "unsigned int",
                        "name": "TP_DIM_R_LEADING",
                        "description": "Describes which dimension of the Matrix Q output data is contigious in memory. TP_DIM_R_LEADING=1 is row major, and TP_DIM_R_LEADING=0 is column major."
                    }
                ],
                "header_file_name": [
                    "qrd_graph.hpp"
                ],
                "instance": "class",
                "api_name": "xf::solver::aie::qrd::qrd_graph",
                "ports": [
                    {
                        "direction": "input",
                        "type": "input_port xf::solver::aie::qrd::qrd_graph< TT_DATA, TP_DIM_ROWS, TP_DIM_COLS, TP_NUM_FRAMES,TP_CASC_LEN>::inA",
                        "name": "inA"
                    },
                    {
                        "direction": "output",
                        "type": "output_port xf::solver::aie::qrd::qrd_graph< TT_DATA, TP_DIM_ROWS, TP_DIM_COLS, TP_NUM_FRAMES,TP_CASC_LEN>::outQ",
                        "name": "outQ"
                    },
                    {
                        "direction": "output",
                        "type": "output_port xf::solver::aie::qrd::qrd_graph< TT_DATA, TP_DIM_ROWS, TP_DIM_COLS, TP_NUM_FRAMES,TP_CASC_LEN>::outR",
                        "name": "outR"
                    }
                ],
                "schema": "vitis_libraries_api_list_schema-1.0"
            }
        }
    ]
}
